{
  "version": "3.6.1",
  "flags": {},
  "shapes": [
    {
      "label": "tail",
      "line_color": null,
      "fill_color": null,
      "points": [
        [
          29,
          114
        ],
        [
          21,
          115
        ],
        [
          14,
          123
        ],
        [
          18,
          136
        ],
        [
          28,
          155
        ],
        [
          48,
          172
        ],
        [
          67,
          188
        ],
        [
          81,
          194
        ],
        [
          105,
          211
        ],
        [
          128,
          224
        ],
        [
          149,
          238
        ],
        [
          167,
          248
        ],
        [
          178,
          253
        ],
        [
          210,
          258
        ],
        [
          234,
          260
        ],
        [
          255,
          253
        ],
        [
          285,
          233
        ],
        [
          329,
          207
        ],
        [
          356,
          189
        ],
        [
          369,
          175
        ],
        [
          378,
          161
        ],
        [
          376,
          136
        ],
        [
          369,
          126
        ],
        [
          361,
          122
        ],
        [
          353,
          128
        ],
        [
          347,
          133
        ],
        [
          333,
          135
        ],
        [
          310,
          141
        ],
        [
          287,
          147
        ],
        [
          257,
          160
        ],
        [
          234,
          166
        ],
        [
          210,
          175
        ],
        [
          201,
          185
        ],
        [
          194,
          178
        ],
        [
          186,
          174
        ],
        [
          177,
          170
        ],
        [
          165,
          164
        ],
        [
          145,
          159
        ],
        [
          129,
          153
        ],
        [
          114,
          148
        ],
        [
          96,
          140
        ],
        [
          80,
          135
        ],
        [
          56,
          130
        ],
        [
          41,
          122
        ]
      ],
      "shape_type": "polygon"
    }
  ],
  "lineColor": [
    0,
    255,
    0,
    128
  ],
  "fillColor": [
    255,
    0,
    0,
    128
  ],
  "imagePath": "004e8ad5b.jpg",
  "imageData": null,
  "imageHeight": 400,
  "imageWidth": 400
}