{
  "version": "3.6.1",
  "flags": {},
  "shapes": [
    {
      "label": "tail",
      "line_color": null,
      "fill_color": null,
      "points": [
        [
          17,
          117
        ],
        [
          3,
          117
        ],
        [
          4,
          125
        ],
        [
          14,
          133
        ],
        [
          35,
          148
        ],
        [
          72,
          168
        ],
        [
          107,
          182
        ],
        [
          134,
          198
        ],
        [
          155,
          209
        ],
        [
          166,
          216
        ],
        [
          178,
          219
        ],
        [
          200,
          218
        ],
        [
          231,
          219
        ],
        [
          250,
          223
        ],
        [
          286,
          225
        ],
        [
          316,
          228
        ],
        [
          342,
          228
        ],
        [
          361,
          232
        ],
        [
          369,
          230
        ],
        [
          378,
          221
        ],
        [
          389,
          206
        ],
        [
          395,
          191
        ],
        [
          396,
          179
        ],
        [
          389,
          176
        ],
        [
          382,
          175
        ],
        [
          373,
          170
        ],
        [
          364,
          163
        ],
        [
          357,
          155
        ],
        [
          345,
          149
        ],
        [
          331,
          145
        ],
        [
          320,
          146
        ],
        [
          308,
          148
        ],
        [
          291,
          151
        ],
        [
          289,
          157
        ],
        [
          294,
          164
        ],
        [
          298,
          170
        ],
        [
          290,
          165
        ],
        [
          282,
          161
        ],
        [
          276,
          157
        ],
        [
          269,
          160
        ],
        [
          265,
          162
        ],
        [
          258,
          158
        ],
        [
          258,
          164
        ],
        [
          255,
          165
        ],
        [
          248,
          164
        ],
        [
          246,
          171
        ],
        [
          240,
          171
        ],
        [
          234,
          173
        ],
        [
          228,
          175
        ],
        [
          223,
          177
        ],
        [
          220,
          181
        ],
        [
          222,
          189
        ],
        [
          223,
          194
        ],
        [
          218,
          189
        ],
        [
          206,
          180
        ],
        [
          182,
          167
        ],
        [
          141,
          149
        ],
        [
          134,
          147
        ],
        [
          116,
          139
        ],
        [
          103,
          135
        ],
        [
          89,
          129
        ],
        [
          58,
          126
        ],
        [
          40,
          123
        ]
      ],
      "shape_type": "polygon"
    }
  ],
  "lineColor": [
    0,
    255,
    0,
    128
  ],
  "fillColor": [
    255,
    0,
    0,
    128
  ],
  "imagePath": "00514c876.jpg",
  "imageData": null,
  "imageHeight": 400,
  "imageWidth": 400
}