{
  "version": "3.6.1",
  "flags": {},
  "shapes": [
    {
      "label": "tail",
      "line_color": null,
      "fill_color": null,
      "points": [
        [
          31,
          136
        ],
        [
          22,
          132
        ],
        [
          14,
          134
        ],
        [
          8,
          138
        ],
        [
          8,
          151
        ],
        [
          9,
          165
        ],
        [
          18,
          176
        ],
        [
          35,
          180
        ],
        [
          51,
          180
        ],
        [
          75,
          182
        ],
        [
          125,
          190
        ],
        [
          151,
          196
        ],
        [
          172,
          202
        ],
        [
          180,
          206
        ],
        [
          193,
          208
        ],
        [
          209,
          198
        ],
        [
          225,
          196
        ],
        [
          241,
          194
        ],
        [
          270,
          190
        ],
        [
          301,
          185
        ],
        [
          328,
          182
        ],
        [
          350,
          181
        ],
        [
          369,
          177
        ],
        [
          380,
          170
        ],
        [
          386,
          162
        ],
        [
          391,
          149
        ],
        [
          391,
          143
        ],
        [
          385,
          136
        ],
        [
          380,
          134
        ],
        [
          375,
          139
        ],
        [
          369,
          143
        ],
        [
          363,
          142
        ],
        [
          356,
          140
        ],
        [
          349,
          136
        ],
        [
          341,
          135
        ],
        [
          336,
          133
        ],
        [
          329,
          132
        ],
        [
          320,
          130
        ],
        [
          307,
          132
        ],
        [
          300,
          130
        ],
        [
          294,
          130
        ],
        [
          288,
          130
        ],
        [
          276,
          130
        ],
        [
          265,
          130
        ],
        [
          256,
          132
        ],
        [
          248,
          132
        ],
        [
          238,
          134
        ],
        [
          229,
          135
        ],
        [
          220,
          137
        ],
        [
          207,
          140
        ],
        [
          197,
          145
        ],
        [
          193,
          143
        ],
        [
          176,
          135
        ],
        [
          165,
          132
        ],
        [
          157,
          131
        ],
        [
          150,
          129
        ],
        [
          140,
          127
        ],
        [
          132,
          126
        ],
        [
          125,
          125
        ],
        [
          116,
          123
        ],
        [
          105,
          123
        ],
        [
          89,
          122
        ],
        [
          80,
          124
        ],
        [
          67,
          126
        ],
        [
          59,
          129
        ],
        [
          51,
          130
        ],
        [
          37,
          133
        ]
      ],
      "shape_type": "polygon"
    }
  ],
  "lineColor": [
    0,
    255,
    0,
    128
  ],
  "fillColor": [
    255,
    0,
    0,
    128
  ],
  "imagePath": "0165c60f3.jpg",
  "imageData": null,
  "imageHeight": 400,
  "imageWidth": 400
}