{
  "version": "3.6.1",
  "flags": {},
  "shapes": [
    {
      "label": "tail",
      "line_color": null,
      "fill_color": null,
      "points": [
        [
          52,
          119
        ],
        [
          44,
          117
        ],
        [
          36,
          111
        ],
        [
          33,
          102
        ],
        [
          32,
          92
        ],
        [
          28,
          92
        ],
        [
          20,
          95
        ],
        [
          13,
          102
        ],
        [
          14,
          113
        ],
        [
          15,
          129
        ],
        [
          20,
          157
        ],
        [
          35,
          183
        ],
        [
          61,
          209
        ],
        [
          103,
          236
        ],
        [
          155,
          260
        ],
        [
          184,
          275
        ],
        [
          212,
          289
        ],
        [
          227,
          300
        ],
        [
          232,
          309
        ],
        [
          233,
          313
        ],
        [
          290,
          313
        ],
        [
          296,
          282
        ],
        [
          318,
          257
        ],
        [
          348,
          229
        ],
        [
          375,
          194
        ],
        [
          390,
          169
        ],
        [
          391,
          148
        ],
        [
          390,
          136
        ],
        [
          387,
          125
        ],
        [
          385,
          120
        ],
        [
          380,
          118
        ],
        [
          370,
          119
        ],
        [
          361,
          122
        ],
        [
          352,
          125
        ],
        [
          344,
          126
        ],
        [
          337,
          126
        ],
        [
          331,
          130
        ],
        [
          326,
          128
        ],
        [
          322,
          128
        ],
        [
          319,
          132
        ],
        [
          314,
          135
        ],
        [
          309,
          138
        ],
        [
          307,
          141
        ],
        [
          302,
          143
        ],
        [
          297,
          146
        ],
        [
          293,
          149
        ],
        [
          288,
          153
        ],
        [
          285,
          155
        ],
        [
          280,
          158
        ],
        [
          272,
          162
        ],
        [
          267,
          165
        ],
        [
          264,
          168
        ],
        [
          258,
          172
        ],
        [
          253,
          177
        ],
        [
          247,
          181
        ],
        [
          244,
          187
        ],
        [
          240,
          192
        ],
        [
          239,
          198
        ],
        [
          239,
          201
        ],
        [
          235,
          198
        ],
        [
          231,
          193
        ],
        [
          229,
          188
        ],
        [
          215,
          183
        ],
        [
          208,
          178
        ],
        [
          192,
          172
        ],
        [
          184,
          168
        ],
        [
          174,
          165
        ],
        [
          168,
          163
        ],
        [
          163,
          163
        ],
        [
          161,
          158
        ],
        [
          155,
          155
        ],
        [
          151,
          153
        ],
        [
          145,
          151
        ],
        [
          140,
          150
        ],
        [
          133,
          147
        ],
        [
          125,
          142
        ],
        [
          119,
          140
        ],
        [
          112,
          135
        ],
        [
          108,
          134
        ],
        [
          104,
          131
        ],
        [
          98,
          128
        ],
        [
          93,
          127
        ],
        [
          88,
          126
        ],
        [
          83,
          124
        ],
        [
          77,
          123
        ],
        [
          72,
          122
        ],
        [
          67,
          121
        ]
      ],
      "shape_type": "polygon"
    }
  ],
  "lineColor": [
    0,
    255,
    0,
    128
  ],
  "fillColor": [
    255,
    0,
    0,
    128
  ],
  "imagePath": "028c4bfde.jpg",
  "imageData": null,
  "imageHeight": 400,
  "imageWidth": 400
}