{
  "version": "3.6.1",
  "flags": {},
  "shapes": [
    {
      "label": "tail",
      "line_color": null,
      "fill_color": null,
      "points": [
        [
          120,
          189
        ],
        [
          90,
          184
        ],
        [
          74,
          181
        ],
        [
          51,
          177
        ],
        [
          29,
          173
        ],
        [
          10,
          176
        ],
        [
          3,
          181
        ],
        [
          3,
          188
        ],
        [
          14,
          194
        ],
        [
          27,
          190
        ],
        [
          44,
          191
        ],
        [
          63,
          198
        ],
        [
          80,
          206
        ],
        [
          97,
          214
        ],
        [
          120,
          223
        ],
        [
          136,
          230
        ],
        [
          151,
          240
        ],
        [
          156,
          246
        ],
        [
          176,
          253
        ],
        [
          188,
          254
        ],
        [
          206,
          251
        ],
        [
          218,
          243
        ],
        [
          230,
          232
        ],
        [
          247,
          226
        ],
        [
          269,
          219
        ],
        [
          296,
          207
        ],
        [
          325,
          198
        ],
        [
          357,
          193
        ],
        [
          378,
          190
        ],
        [
          389,
          191
        ],
        [
          395,
          191
        ],
        [
          398,
          180
        ],
        [
          392,
          179
        ],
        [
          376,
          178
        ],
        [
          363,
          179
        ],
        [
          353,
          180
        ],
        [
          331,
          182
        ],
        [
          307,
          183
        ],
        [
          284,
          185
        ],
        [
          248,
          189
        ],
        [
          215,
          192
        ],
        [
          197,
          194
        ],
        [
          184,
          194
        ],
        [
          162,
          196
        ],
        [
          144,
          194
        ]
      ],
      "shape_type": "polygon"
    }
  ],
  "lineColor": [
    0,
    255,
    0,
    128
  ],
  "fillColor": [
    255,
    0,
    0,
    128
  ],
  "imagePath": "04931bb7a.jpg",
  "imageData": null,
  "imageHeight": 400,
  "imageWidth": 400
}